ConfluentKafkaLibrary/__init__.py
ConfluentKafkaLibrary/admin_client.py
ConfluentKafkaLibrary/consumer.py
ConfluentKafkaLibrary/producer.py
ConfluentKafkaLibrary/serialization.py
ConfluentKafkaLibrary/version.py
robotframework_confluentkafkalibrary-2.12.2.post1.dist-info/licenses/LICENSE
robotframework_confluentkafkalibrary-2.12.2.post1.dist-info/METADATA
robotframework_confluentkafkalibrary-2.12.2.post1.dist-info/WHEEL
robotframework_confluentkafkalibrary-2.12.2.post1.dist-info/top_level.txt
robotframework_confluentkafkalibrary-2.12.2.post1.dist-info/RECORD
