Metadata-Version: 2.4
Name: robotframework-confluentkafkalibrary
Version: 2.12.2.post1
Summary: Confluent Kafka library for Robot Framework
Author-email: Robert Karasek <robo.karasek@gmail.com>
License-Expression: Apache-2.0
Project-URL: Homepage, https://github.com/robooo/robotframework-ConfluentKafkaLibrary
Keywords: robotframework,confluent,kafka
Classifier: Operating System :: OS Independent
Classifier: Programming Language :: Python
Classifier: Topic :: Software Development :: Testing
Requires-Python: >=3.8
License-File: LICENSE
Requires-Dist: robotframework>=3.2.1
Requires-Dist: confluent-kafka==2.12.2
Requires-Dist: requests>=2.25.1
Provides-Extra: avro
Requires-Dist: fastavro>=1.3.2; extra == "avro"
Requires-Dist: avro>=1.11.1; extra == "avro"
Provides-Extra: json
Requires-Dist: jsonschema>=3.2.0; extra == "json"
Requires-Dist: pyrsistent>=0.20.0; extra == "json"
Requires-Dist: orjson>=3.10; extra == "json"
Provides-Extra: protobuf
Requires-Dist: protobuf>=4.22.0; extra == "protobuf"
Requires-Dist: googleapis-common-protos>=1.66.0; extra == "protobuf"
Provides-Extra: schemaregistry
Requires-Dist: httpx>=0.26; extra == "schemaregistry"
Requires-Dist: cachetools>=5.5.0; extra == "schemaregistry"
Requires-Dist: attrs>=24.3.0; extra == "schemaregistry"
Requires-Dist: certifi; extra == "schemaregistry"
Requires-Dist: authlib>=1.0.0; extra == "schemaregistry"
Provides-Extra: all
Requires-Dist: robotframework-confluentkafkalibrary[avro]; extra == "all"
Requires-Dist: robotframework-confluentkafkalibrary[json]; extra == "all"
Requires-Dist: robotframework-confluentkafkalibrary[protobuf]; extra == "all"
Requires-Dist: robotframework-confluentkafkalibrary[schemaregistry]; extra == "all"
Dynamic: license-file
